flask_api_starter/__init__.py
flask_api_starter/cli.py
flask_api_starter/templates/requirements.txt
flask_api_starter/templates/run.py
flask_api_starter/templates/app/__init__.py
flask_api_starter/templates/app/config.py
flask_api_starter/templates/app/database.py
flask_api_starter/templates/app/extensions.py
flask_api_starter/templates/app/blueprints/api/__init__.py
flask_api_starter/templates/app/blueprints/api/routes.py
flask_api_starter/templates/app/blueprints/auth/__init__.py
flask_api_starter/templates/app/blueprints/auth/routes.py
flask_api_starter/templates/app/constants/http_status_codes.py
flask_api_starter/templates/app/constants/__pycache__/http_status_codes.cpython-313.pyc
flask_api_starter/templates/app/models/user.py
flask_api_starter/templates/app/static/swagger.yaml
flask_api_starter/templates/app/utils/token.py
flask_api_starter-1.1.3.dist-info/licenses/LICENSE
flask_api_starter-1.1.3.dist-info/METADATA
flask_api_starter-1.1.3.dist-info/WHEEL
flask_api_starter-1.1.3.dist-info/entry_points.txt
flask_api_starter-1.1.3.dist-info/top_level.txt
flask_api_starter-1.1.3.dist-info/RECORD
