Metadata-Version: 2.4
Name: flask-api-starter
Version: 1.1.3
Summary: A scalable Flask API starter with authentication, blueprints, DB setup, full project generator, and documentation setup using swaggerUI.
Author-email: Paul Mkundika Jr <authenticpaulmeyers@gmail.com>
Requires-Python: >=3.9
License-File: LICENSE
Requires-Dist: click
Requires-Dist: Flask
Requires-Dist: Flask-JWT-Extended
Requires-Dist: Flask-Migrate
Requires-Dist: Flask-SQLAlchemy
Requires-Dist: python-dotenv
Requires-Dist: Werkzeug
Requires-Dist: validators
Dynamic: license-file
